PAPER/__init__.py
PAPER/estimateAlpha.py
PAPER/gibbsSampling.py
PAPER/grafting.py
PAPER/tree_tools.py
paper_network-0.0.1.dist-info/LICENSE.txt
paper_network-0.0.1.dist-info/METADATA
paper_network-0.0.1.dist-info/WHEEL
paper_network-0.0.1.dist-info/top_level.txt
paper_network-0.0.1.dist-info/RECORD
