Metadata-Version: 2.1
Name: paper-network
Version: 0.0.1
Summary: Gibbs Sampler and other functions for PAPER (Preferential Attachment Plus Erdos--Renyi) model for random networks
Home-page: https://github.com/nineisprime/PAPER
Author: Min Xu
Author-email: mx76@stat.rutgers.edu
License: UNKNOWN
Platform: UNKNOWN
Classifier: Programming Language :: Python :: 3
Classifier: Programming Language :: Python :: 3.7
Classifier: Programming Language :: Python :: 3.8
Classifier: Programming Language :: Python :: 3.9
Classifier: License :: OSI Approved :: GNU General Public License (GPL)
Classifier: Operating System :: OS Independent
Classifier: Topic :: Scientific/Engineering :: Mathematics
Classifier: Topic :: Scientific/Engineering
Requires-Dist: python-igraph
Requires-Dist: numpy
